{
  "2025": {
    "token_count": 19338,
    "unique_token_count": 2594,
    "Negative_count": 716,
    "Positive_count": 134,
    "Uncertainty_count": 561,
    "Litigious_count": 296,
    "Strong_Modal_count": 59,
    "Weak_Modal_count": 383,
    "Constraining_count": 320,
    "Negative_ratio": 0.03702554555796877,
    "Positive_ratio": 0.0069293618781673385,
    "Uncertainty_ratio": 0.02901023890784983,
    "Litigious_ratio": 0.015306650118936808,
    "Strong_Modal_ratio": 0.003050987692625918,
    "Weak_Modal_ratio": 0.019805564174164857,
    "Constraining_ratio": 0.016547729858310063,
    "NetNegative_ratio": 0.03009618367980143
  },
  "2024": {
    "token_count": 19591,
    "unique_token_count": 2518,
    "Negative_count": 682,
    "Positive_count": 165,
    "Uncertainty_count": 587,
    "Litigious_count": 282,
    "Strong_Modal_count": 70,
    "Weak_Modal_count": 392,
    "Constraining_count": 319,
    "Negative_ratio": 0.03481190342504211,
    "Positive_ratio": 0.008422234699606962,
    "Uncertainty_ratio": 0.029962737991935072,
    "Litigious_ratio": 0.014394364759328263,
    "Strong_Modal_ratio": 0.0035730692664999236,
    "Weak_Modal_ratio": 0.020009187892399572,
    "Constraining_ratio": 0.016282987085906794,
    "NetNegative_ratio": 0.026389668725435148
  },
  "2023": {
    "token_count": 19408,
    "unique_token_count": 2422,
    "Negative_count": 670,
    "Positive_count": 180,
    "Uncertainty_count": 613,
    "Litigious_count": 254,
    "Strong_Modal_count": 78,
    "Weak_Modal_count": 415,
    "Constraining_count": 292,
    "Negative_ratio": 0.03452184666117065,
    "Positive_ratio": 0.009274525968672712,
    "Uncertainty_ratio": 0.03158491343775763,
    "Litigious_ratio": 0.013087386644682605,
    "Strong_Modal_ratio": 0.004018961253091508,
    "Weak_Modal_ratio": 0.02138293487221764,
    "Constraining_ratio": 0.015045342126957956,
    "NetNegative_ratio": 0.025247320692497938
  },
  "2022": {
    "token_count": 13356,
    "unique_token_count": 2134,
    "Negative_count": 455,
    "Positive_count": 120,
    "Uncertainty_count": 393,
    "Litigious_count": 178,
    "Strong_Modal_count": 45,
    "Weak_Modal_count": 248,
    "Constraining_count": 207,
    "Negative_ratio": 0.034067085953878404,
    "Positive_ratio": 0.008984725965858042,
    "Uncertainty_ratio": 0.029424977538185085,
    "Litigious_ratio": 0.013327343516022761,
    "Strong_Modal_ratio": 0.0033692722371967657,
    "Weak_Modal_ratio": 0.018568433662773286,
    "Constraining_ratio": 0.01549865229110512,
    "NetNegative_ratio": 0.025082359988020362
  },
  "2021": {
    "token_count": 17045,
    "unique_token_count": 2267,
    "Negative_count": 579,
    "Positive_count": 167,
    "Uncertainty_count": 559,
    "Litigious_count": 207,
    "Strong_Modal_count": 76,
    "Weak_Modal_count": 363,
    "Constraining_count": 238,
    "Negative_ratio": 0.033968905837489,
    "Positive_ratio": 0.009797594602522735,
    "Uncertainty_ratio": 0.032795541214432386,
    "Litigious_ratio": 0.012144323848635964,
    "Strong_Modal_ratio": 0.004458785567615136,
    "Weak_Modal_ratio": 0.02129656790847756,
    "Constraining_ratio": 0.013963039014373716,
    "NetNegative_ratio": 0.02417131123496627
  },
  "2020": {
    "token_count": 12292,
    "unique_token_count": 2011,
    "Negative_count": 409,
    "Positive_count": 103,
    "Uncertainty_count": 349,
    "Litigious_count": 138,
    "Strong_Modal_count": 47,
    "Weak_Modal_count": 222,
    "Constraining_count": 187,
    "Negative_ratio": 0.03327367393426619,
    "Positive_ratio": 0.008379433778067035,
    "Uncertainty_ratio": 0.02839245037422714,
    "Litigious_ratio": 0.011226814188089814,
    "Strong_Modal_ratio": 0.003823625122030589,
    "Weak_Modal_ratio": 0.018060527172144483,
    "Constraining_ratio": 0.015213146762121705,
    "NetNegative_ratio": 0.024894240156199156
  },
  "2019": {
    "token_count": 12472,
    "unique_token_count": 1810,
    "Negative_count": 436,
    "Positive_count": 100,
    "Uncertainty_count": 385,
    "Litigious_count": 148,
    "Strong_Modal_count": 42,
    "Weak_Modal_count": 261,
    "Constraining_count": 215,
    "Negative_ratio": 0.03495830660679923,
    "Positive_ratio": 0.008017960230917255,
    "Uncertainty_ratio": 0.030869146889031432,
    "Litigious_ratio": 0.011866581141757537,
    "Strong_Modal_ratio": 0.003367543296985247,
    "Weak_Modal_ratio": 0.020926876202694036,
    "Constraining_ratio": 0.0172386144964721,
    "NetNegative_ratio": 0.026940346375881975
  },
  "2018": {
    "token_count": 11166,
    "unique_token_count": 1649,
    "Negative_count": 375,
    "Positive_count": 82,
    "Uncertainty_count": 368,
    "Litigious_count": 131,
    "Strong_Modal_count": 41,
    "Weak_Modal_count": 252,
    "Constraining_count": 199,
    "Negative_ratio": 0.033584094572810315,
    "Positive_ratio": 0.007343722013254523,
    "Uncertainty_ratio": 0.03295719147411786,
    "Litigious_ratio": 0.011732043704101738,
    "Strong_Modal_ratio": 0.0036718610066272615,
    "Weak_Modal_ratio": 0.022568511552928532,
    "Constraining_ratio": 0.017821959519971342,
    "NetNegative_ratio": 0.026240372559555792
  },
  "2017": {
    "token_count": 11627,
    "unique_token_count": 1771,
    "Negative_count": 385,
    "Positive_count": 70,
    "Uncertainty_count": 342,
    "Litigious_count": 183,
    "Strong_Modal_count": 37,
    "Weak_Modal_count": 227,
    "Constraining_count": 227,
    "Negative_ratio": 0.033112582781456956,
    "Positive_ratio": 0.006020469596628537,
    "Uncertainty_ratio": 0.02941429431495657,
    "Litigious_ratio": 0.015739227659757462,
    "Strong_Modal_ratio": 0.003182248215360798,
    "Weak_Modal_ratio": 0.019523522834781114,
    "Constraining_ratio": 0.019523522834781114,
    "NetNegative_ratio": 0.027092113184828417
  }
}