{
  "2023": {
    "token_count": 37685,
    "unique_token_count": 3322,
    "Negative_count": 1593,
    "Positive_count": 298,
    "Uncertainty_count": 1118,
    "Litigious_count": 902,
    "Strong_Modal_count": 118,
    "Weak_Modal_count": 788,
    "Constraining_count": 463,
    "Negative_ratio": 0.04227146079341913,
    "Positive_ratio": 0.007907655565875017,
    "Uncertainty_ratio": 0.029666976250497544,
    "Litigious_ratio": 0.023935252753084783,
    "Strong_Modal_ratio": 0.003131219318031047,
    "Weak_Modal_ratio": 0.020910176462783602,
    "Constraining_ratio": 0.01228605545973199,
    "NetNegative_ratio": 0.03436380522754412
  },
  "2022": {
    "token_count": 38317,
    "unique_token_count": 3353,
    "Negative_count": 1625,
    "Positive_count": 304,
    "Uncertainty_count": 1134,
    "Litigious_count": 902,
    "Strong_Modal_count": 115,
    "Weak_Modal_count": 800,
    "Constraining_count": 475,
    "Negative_ratio": 0.04240937442910458,
    "Positive_ratio": 0.007933815277814026,
    "Uncertainty_ratio": 0.029595218832372053,
    "Litigious_ratio": 0.02354046506772451,
    "Strong_Modal_ratio": 0.003001278805752016,
    "Weak_Modal_ratio": 0.02087846125740533,
    "Constraining_ratio": 0.012396586371584414,
    "NetNegative_ratio": 0.03447555915129055
  },
  "2021": {
    "token_count": 37597,
    "unique_token_count": 3477,
    "Negative_count": 1493,
    "Positive_count": 311,
    "Uncertainty_count": 1090,
    "Litigious_count": 904,
    "Strong_Modal_count": 113,
    "Weak_Modal_count": 761,
    "Constraining_count": 463,
    "Negative_ratio": 0.03971061520866027,
    "Positive_ratio": 0.008271936590685426,
    "Uncertainty_ratio": 0.028991674867675614,
    "Litigious_ratio": 0.024044471633375003,
    "Strong_Modal_ratio": 0.0030055589541718754,
    "Weak_Modal_ratio": 0.020240976673670773,
    "Constraining_ratio": 0.012314812352049365,
    "NetNegative_ratio": 0.03143867861797484
  },
  "2020": {
    "token_count": 35192,
    "unique_token_count": 3409,
    "Negative_count": 1388,
    "Positive_count": 286,
    "Uncertainty_count": 1004,
    "Litigious_count": 839,
    "Strong_Modal_count": 115,
    "Weak_Modal_count": 709,
    "Constraining_count": 451,
    "Negative_ratio": 0.03944078199590816,
    "Positive_ratio": 0.008126847010684246,
    "Uncertainty_ratio": 0.02852921118436008,
    "Litigious_ratio": 0.023840645601273018,
    "Strong_Modal_ratio": 0.0032677881336667424,
    "Weak_Modal_ratio": 0.02014662423278018,
    "Constraining_ratio": 0.012815412593771312,
    "NetNegative_ratio": 0.03131393498522392
  },
  "2019": {
    "token_count": 32955,
    "unique_token_count": 3242,
    "Negative_count": 1280,
    "Positive_count": 255,
    "Uncertainty_count": 885,
    "Litigious_count": 800,
    "Strong_Modal_count": 113,
    "Weak_Modal_count": 635,
    "Constraining_count": 414,
    "Negative_ratio": 0.03884084357457138,
    "Positive_ratio": 0.007737824305871643,
    "Uncertainty_ratio": 0.026854802002730997,
    "Litigious_ratio": 0.024275527234107117,
    "Strong_Modal_ratio": 0.0034289182218176302,
    "Weak_Modal_ratio": 0.01926869974207252,
    "Constraining_ratio": 0.012562585343650432,
    "NetNegative_ratio": 0.03110301926869974
  },
  "2018": {
    "token_count": 33326,
    "unique_token_count": 3209,
    "Negative_count": 1286,
    "Positive_count": 288,
    "Uncertainty_count": 881,
    "Litigious_count": 788,
    "Strong_Modal_count": 128,
    "Weak_Modal_count": 630,
    "Constraining_count": 424,
    "Negative_ratio": 0.03858848946768289,
    "Positive_ratio": 0.008641901218268019,
    "Uncertainty_ratio": 0.02643581587949349,
    "Litigious_ratio": 0.023645201944427773,
    "Strong_Modal_ratio": 0.0038408449858968975,
    "Weak_Modal_ratio": 0.01890415891496129,
    "Constraining_ratio": 0.012722799015783472,
    "NetNegative_ratio": 0.02994658824941487
  },
  "2017": {
    "token_count": 27597,
    "unique_token_count": 2955,
    "Negative_count": 1086,
    "Positive_count": 253,
    "Uncertainty_count": 709,
    "Litigious_count": 637,
    "Strong_Modal_count": 98,
    "Weak_Modal_count": 508,
    "Constraining_count": 356,
    "Negative_ratio": 0.03935210348950973,
    "Positive_ratio": 0.009167663151791862,
    "Uncertainty_ratio": 0.025691198318657824,
    "Litigious_ratio": 0.02308221908178425,
    "Strong_Modal_ratio": 0.003551110627966808,
    "Weak_Modal_ratio": 0.018407797949052434,
    "Constraining_ratio": 0.012899952893430445,
    "NetNegative_ratio": 0.030184440337717867
  },
  "2016": {
    "token_count": 24403,
    "unique_token_count": 2791,
    "Negative_count": 919,
    "Positive_count": 227,
    "Uncertainty_count": 611,
    "Litigious_count": 542,
    "Strong_Modal_count": 100,
    "Weak_Modal_count": 424,
    "Constraining_count": 332,
    "Negative_ratio": 0.037659304183911814,
    "Positive_ratio": 0.00930213498340368,
    "Uncertainty_ratio": 0.025037905175593164,
    "Litigious_ratio": 0.022210383969184115,
    "Strong_Modal_ratio": 0.004097856820882678,
    "Weak_Modal_ratio": 0.017374912920542555,
    "Constraining_ratio": 0.013604884645330492,
    "NetNegative_ratio": 0.028357169200508132
  }
}