{
  "2025": {
    "token_count": 29177,
    "unique_token_count": 2866,
    "Negative_count": 1280,
    "Positive_count": 233,
    "Uncertainty_count": 915,
    "Litigious_count": 538,
    "Strong_Modal_count": 67,
    "Weak_Modal_count": 512,
    "Constraining_count": 388,
    "Negative_ratio": 0.04387017171059396,
    "Positive_ratio": 0.007985742194194057,
    "Uncertainty_ratio": 0.0313603180587449,
    "Litigious_ratio": 0.018439181547109024,
    "Strong_Modal_ratio": 0.0022963293004764026,
    "Weak_Modal_ratio": 0.017548068684237583,
    "Constraining_ratio": 0.013298145799773795,
    "NetNegative_ratio": 0.035884429516399904
  },
  "2024": {
    "token_count": 18290,
    "unique_token_count": 2183,
    "Negative_count": 965,
    "Positive_count": 120,
    "Uncertainty_count": 717,
    "Litigious_count": 359,
    "Strong_Modal_count": 37,
    "Weak_Modal_count": 390,
    "Constraining_count": 185,
    "Negative_ratio": 0.05276107162383816,
    "Positive_ratio": 0.0065609622744669215,
    "Uncertainty_ratio": 0.039201749589939855,
    "Litigious_ratio": 0.019628212137780206,
    "Strong_Modal_ratio": 0.002022963367960634,
    "Weak_Modal_ratio": 0.021323127392017496,
    "Constraining_ratio": 0.010114816839803172,
    "NetNegative_ratio": 0.04620010934937124
  },
  "2023": {
    "token_count": 17846,
    "unique_token_count": 2155,
    "Negative_count": 988,
    "Positive_count": 122,
    "Uncertainty_count": 699,
    "Litigious_count": 359,
    "Strong_Modal_count": 49,
    "Weak_Modal_count": 401,
    "Constraining_count": 195,
    "Negative_ratio": 0.0553625462288468,
    "Positive_ratio": 0.006836265829877844,
    "Uncertainty_ratio": 0.03916844110725092,
    "Litigious_ratio": 0.020116552728902837,
    "Strong_Modal_ratio": 0.0027457133251148715,
    "Weak_Modal_ratio": 0.022470021293287012,
    "Constraining_ratio": 0.010926818334640816,
    "NetNegative_ratio": 0.04852628039896896
  },
  "2022": {
    "token_count": 14393,
    "unique_token_count": 1899,
    "Negative_count": 759,
    "Positive_count": 90,
    "Uncertainty_count": 576,
    "Litigious_count": 298,
    "Strong_Modal_count": 35,
    "Weak_Modal_count": 346,
    "Constraining_count": 161,
    "Negative_ratio": 0.052733967901063016,
    "Positive_ratio": 0.006253039672062808,
    "Uncertainty_ratio": 0.04001945390120197,
    "Litigious_ratio": 0.020704509136385742,
    "Strong_Modal_ratio": 0.0024317376502466475,
    "Weak_Modal_ratio": 0.024039463628152576,
    "Constraining_ratio": 0.011185993191134579,
    "NetNegative_ratio": 0.046480928229000205
  }
}